sms_stack/__init__.py
sms_stack/cipher.py
sms_stack/sms_broadcaster.py
sms_stack/sms_controller_observer.py
sms_stack/sms_received.py
sms_stack/sms_tcp.py
sms_stack/sms_tcp_controller.py
sms_stack/sms_tcp_layer.py
sms_stack/sms_tcp_layer_formatter.py
sms_stack/sms_tcp_receiver.py
sms_stack/sms_tcp_sender.py
sms_stack/debug/__init__.py
sms_stack/debug/sms_broadcast_im.py
sms_stack/debug/sms_mt_controller.py
sms_stack/debug/sms_mt_layer.py
sms_stack/test/__init__.py
sms_stack/test/test_sms_tcp_receiver.py
sms_stack-1.1.0.dist-info/LICENSE
sms_stack-1.1.0.dist-info/METADATA
sms_stack-1.1.0.dist-info/WHEEL
sms_stack-1.1.0.dist-info/top_level.txt
sms_stack-1.1.0.dist-info/RECORD
