Metadata-Version: 2.1
Name: sms-stack
Version: 1.1.0
Summary: Sms Stack SDK for python
Home-page: UNKNOWN
Author: Lucas Fernandez
Author-email: lucas.fernandezaragon@telefonica.com
License: UNKNOWN
Keywords: sms-stack,tcp,protocol
Platform: UNKNOWN
Classifier: Programming Language :: Python :: 3
Classifier: License :: OSI Approved :: MIT License
Classifier: Operating System :: OS Independent
